virtualfish/__init__.py
virtualfish/__main__.py
virtualfish/auto_activation.fish
virtualfish/compat_aliases.fish
virtualfish/environment.fish
virtualfish/global_requirements.fish
virtualfish/loader/__init__.py
virtualfish/loader/cli.py
virtualfish/loader/installer.py
virtualfish/projects.fish
virtualfish/test/__init__.py
virtualfish/test/conftest.py
virtualfish/test/repl.fish
virtualfish/test/repl.py
virtualfish/test/test_activate.py
virtualfish/test/test_addpath.py
virtualfish/test/test_deactivate.py
virtualfish/test/test_loader.py
virtualfish/test/test_repl.py
virtualfish/test/test_rm.py
virtualfish/update_python.fish
virtualfish/virtual.fish
virtualfish-2.5.8.dist-info/LICENSE
virtualfish-2.5.8.dist-info/METADATA
virtualfish-2.5.8.dist-info/WHEEL
virtualfish-2.5.8.dist-info/entry_points.txt
virtualfish-2.5.8.dist-info/RECORD
