Metadata-Version: 2.1
Name: virtualfish
Version: 2.5.8
Summary: Fish shell tool for managing Python virtual environments
Home-page: https://github.com/justinmayer/virtualfish
License: MIT
Keywords: fish,shell,python,virtual,environments,virtualenv
Author: Justin Mayer
Author-email: entroP@gmail.com
Requires-Python: >=3.8,<4.0
Classifier: Development Status :: 5 - Production/Stable
Classifier: Environment :: Console
Classifier: Intended Audience :: End Users/Desktop
Classifier: License :: OSI Approved :: MIT License
Classifier: Operating System :: OS Independent
Classifier: Programming Language :: Python :: 3
Classifier: Programming Language :: Python :: 3.8
Classifier: Programming Language :: Python :: 3.9
Classifier: Programming Language :: Python :: 3.10
Classifier: Programming Language :: Python :: 3.11
Classifier: Programming Language :: Python :: 3.12
Classifier: Topic :: System :: Shells
Requires-Dist: packaging (>=21.3)
Requires-Dist: pkgconfig (>=1.5)
Requires-Dist: psutil (>=5.7)
Requires-Dist: virtualenv (>=20)
Project-URL: Documentation, https://virtualfish.readthedocs.org/
Project-URL: Repository, https://github.com/justinmayer/virtualfish
Project-URL: Tracker, https://github.com/justinmayer/virtualfish/issues
